COPYING
MANIFEST.in
NEWS.rst
README
setup.py
uci-vms
ucivms/__init__.py
ucivms/commands.py
ucivms/config.py
ucivms/errors.py
ucivms/logs.py
ucivms/monitors.py
ucivms/ssh.py
ucivms/subprocesses.py
ucivms/timeouts.py
ucivms.egg-info/PKG-INFO
ucivms.egg-info/SOURCES.txt
ucivms.egg-info/dependency_links.txt
ucivms.egg-info/requires.txt
ucivms.egg-info/top_level.txt
ucivms/tests/__init__.py
ucivms/tests/features.py
ucivms/tests/fixtures.py
ucivms/tests/test_commands.py
ucivms/tests/test_config.py
ucivms/tests/test_fixtures.py
ucivms/tests/test_logs.py
ucivms/tests/test_lxd.py
ucivms/tests/test_monitors.py
ucivms/tests/test_ssh.py
ucivms/tests/test_styles.py
ucivms/tests/test_subprocesses.py
ucivms/tests/test_timeouts.py
ucivms/tests/test_vms.py
ucivms/vms/__init__.py
ucivms/vms/lxd.py
ucivms/vms/nova.py