Metadata-Version: 1.0
Name: ucivms
Version: 0.2.0
Summary: Ubuntu Continuous Integration virtual machine tools.
Home-page: https://launchpad.net/uci-vms
Author: Vincent Ladeuil
Author-email: vila+qa@canonical.com
License: GPLv3
Platform: UNKNOWN
